pygtkhelpers/__init__.py
pygtkhelpers/addons.py
pygtkhelpers/delegates.py
pygtkhelpers/forms.py
pygtkhelpers/gthreads.py
pygtkhelpers/proxy.py
pygtkhelpers/schema.py
pygtkhelpers/test.py
pygtkhelpers/utils.py
pygtkhelpers/debug/__init__.py
pygtkhelpers/debug/console.py
pygtkhelpers/debug/dialogs.py
pygtkhelpers/ui/__init__.py
pygtkhelpers/ui/dialogs.py
pygtkhelpers/ui/dict_as_attr_proxy.py
pygtkhelpers/ui/extra_dialogs.py
pygtkhelpers/ui/extra_widgets.py
pygtkhelpers/ui/form_view_dialog.py
pygtkhelpers/ui/list_select.py
pygtkhelpers/ui/notebook.py
pygtkhelpers/ui/widgets.py
pygtkhelpers/ui/glade/form_view_dialog.glade
pygtkhelpers/ui/objectlist/__init__.py
pygtkhelpers/ui/objectlist/column.py
pygtkhelpers/ui/objectlist/combined_fields.py
pygtkhelpers/ui/objectlist/uuid_minimal.py
pygtkhelpers/ui/objectlist/view.py
pygtkhelpers/ui/views/__init__.py
pygtkhelpers/ui/views/cairo_view.py
pygtkhelpers/ui/views/command_textview.py
pygtkhelpers/ui/views/select.py
pygtkhelpers/ui/views/shapes_canvas_view.py
pygtkhelpers/ui/views/surface.py
pygtkhelpers/ui/views/glade/layers.glade
pygtkhelpers/ui/views/glade/list_select.glade
wheeler.pygtkhelpers-0.14.post7.dist-info/DESCRIPTION.rst
wheeler.pygtkhelpers-0.14.post7.dist-info/METADATA
wheeler.pygtkhelpers-0.14.post7.dist-info/RECORD
wheeler.pygtkhelpers-0.14.post7.dist-info/WHEEL
wheeler.pygtkhelpers-0.14.post7.dist-info/metadata.json
wheeler.pygtkhelpers-0.14.post7.dist-info/pbr.json
wheeler.pygtkhelpers-0.14.post7.dist-info/top_level.txt
