Metadata-Version: 2.0
Name: wheeler.pygtkhelpers
Version: 0.14.post7
Summary: PyGTKHelpers is a library to assist the building of PyGTK applications.
Home-page: https://github.com/wheeler-microfluidics/pygtk_helpers
Author: Christian Fobel
Author-email: christian@fobel.net
License: LGPL-3.0
Platform: UNKNOWN
Requires-Dist: cairo-helpers (>=0.2.post1)
Requires-Dist: flatland-fork (>=0.4.post2)
Requires-Dist: jsonschema
Requires-Dist: redirect-io
Requires-Dist: si-prefix (>=0.4)
Requires-Dist: svg-model (>=0.5.post18)
Requires-Dist: trollius (>=2.1)
